[
 {
  "name": "CHIPS",
  "owner": {
   "login": "privacycg"
  },
  "description": "A proposal for a cookie attribute to partition cross-site cookies by top-level site",
  "isArchived": false,
  "isPrivate": false,
  "w3cjson": {
   "group": [
    "cg/privacycg"
   ],
   "contacts": [
    "cwilso"
   ],
   "repo-type": [
    "cg-report"
   ],
   "exposed": true
  }
 },
 {
  "name": "ad-topic-hints",
  "owner": {
   "login": "privacycg"
  },
  "description": "Ad Topic Hints",
  "isArchived": false,
  "isPrivate": false,
  "w3cjson": {
   "group": [
    "cg/privacycg"
   ],
   "contacts": [
    "hober",
    "TanviHacks",
    "erik-anderson",
    "wseltzer",
    "weiler"
   ],
   "repo-type": [
    "cg-report"
   ],
   "exposed": true
  }
 },
 {
  "name": "admin",
  "owner": {
   "login": "privacycg"
  },
  "homepageUrl": "https://privacycg.github.io",
  "description": "Administrivia for the Privacy Community Group",
  "isArchived": false,
  "isPrivate": false,
  "w3cjson": {
   "group": [
    "cg/privacycg"
   ],
   "contacts": [
    "hober",
    "TanviHacks",
    "erik-anderson",
    "wseltzer",
    "weiler"
   ],
   "repo-type": [
    "others"
   ],
   "policy": "open",
   "exposed": true
  }
 },
 {
  "name": "is-logged-in",
  "owner": {
   "login": "privacycg"
  },
  "description": "The IsLoggedIn API",
  "isArchived": false,
  "isPrivate": false,
  "w3cjson": {
   "group": [
    "cg/privacycg"
   ],
   "contacts": [
    "hober",
    "TanviHacks",
    "erik-anderson",
    "wseltzer",
    "weiler"
   ],
   "repo-type": [
    "cg-report"
   ],
   "exposed": true
  }
 },
 {
  "name": "js-membranes",
  "owner": {
   "login": "privacycg"
  },
  "description": "JS Isolation via Origin Labels and Membranes",
  "isArchived": false,
  "isPrivate": false,
  "w3cjson": {
   "group": [
    "cg/privacycg"
   ],
   "contacts": [
    "hober",
    "TanviHacks",
    "erik-anderson",
    "wseltzer",
    "weiler"
   ],
   "repo-type": [
    "cg-report"
   ],
   "exposed": true
  }
 },
 {
  "name": "meetings",
  "owner": {
   "login": "privacycg"
  },
  "homepageUrl": "https://privacycg.github.io",
  "description": "Agenda and minutes of meetings of the Privacy Community Group",
  "isArchived": false,
  "isPrivate": false,
  "w3cjson": {
   "group": [
    "cg/privacycg"
   ],
   "contacts": [
    "hober",
    "TanviHacks",
    "erik-anderson",
    "wseltzer",
    "weiler"
   ],
   "repo-type": [
    "others"
   ],
   "policy": "open",
   "exposed": true
  }
 },
 {
  "name": "nav-tracking-mitigations",
  "owner": {
   "login": "privacycg"
  },
  "homepageUrl": "https://privacycg.github.io/nav-tracking-mitigations/",
  "description": "Navigation-based Tracking Mitigations",
  "isArchived": false,
  "isPrivate": false,
  "w3cjson": {
   "group": [
    "cg/privacycg"
   ],
   "contacts": [
    "hober",
    "TanviHacks",
    "erik-anderson",
    "wseltzer",
    "weiler"
   ],
   "repo-type": [
    "cg-report"
   ],
   "exposed": true
  }
 },
 {
  "name": "privacycg.github.io",
  "owner": {
   "login": "privacycg"
  },
  "homepageUrl": "https://privacycg.github.io",
  "description": "Website and charter of the Privacy Community Group",
  "isArchived": false,
  "isPrivate": false,
  "w3cjson": {
   "group": [
    "cg/privacycg"
   ],
   "contacts": [
    "hober",
    "martinthomson",
    "erik-anderson",
    "wseltzer",
    "weiler"
   ],
   "repo-type": [
    "homepage"
   ],
   "policy": "open",
   "exposed": true
  }
 },
 {
  "name": "private-click-measurement",
  "owner": {
   "login": "privacycg"
  },
  "homepageUrl": "https://privacycg.github.io/private-click-measurement/",
  "description": "Private Click Measurement",
  "isArchived": false,
  "isPrivate": false,
  "w3cjson": {
   "group": [
    "cg/privacycg"
   ],
   "contacts": [
    "hober",
    "TanviHacks",
    "erik-anderson",
    "wseltzer",
    "weiler"
   ],
   "repo-type": [
    "cg-report"
   ],
   "exposed": true
  }
 },
 {
  "name": "proposals",
  "owner": {
   "login": "privacycg"
  },
  "homepageUrl": "https://privacycg.github.io",
  "description": "New proposals in the Privacy Community Group",
  "isArchived": false,
  "isPrivate": false,
  "w3cjson": {
   "group": [
    "cg/privacycg"
   ],
   "contacts": [
    "hober",
    "TanviHacks",
    "erik-anderson",
    "wseltzer",
    "weiler"
   ],
   "repo-type": [
    "others"
   ],
   "policy": "open",
   "exposed": true
  }
 },
 {
  "name": "requestStorageAccessFor",
  "owner": {
   "login": "privacycg"
  },
  "homepageUrl": "https://privacycg.github.io/requestStorageAccessFor/",
  "description": "A proposed extension to the Storage Access API and discussion of how it may be integrated with First-Party Sets.",
  "isArchived": false,
  "isPrivate": false,
  "w3cjson": {
   "group": [
    "cg/privacycg"
   ],
   "contacts": [
    "hober",
    "martinthomson",
    "erik-anderson",
    "weiler"
   ],
   "repo-type": [
    "cg-report"
   ],
   "exposed": true
  }
 },
 {
  "name": "saa-non-cookie-storage",
  "owner": {
   "login": "privacycg"
  },
  "homepageUrl": "https://privacycg.github.io/saa-non-cookie-storage/",
  "description": "Extending Storage Access API (SAA) to non-cookie storage",
  "isArchived": false,
  "isPrivate": false,
  "w3cjson": {
   "group": [
    "cg/privacycg"
   ],
   "contacts": [
    "arichiv",
    "johannhof"
   ],
   "repo-type": [
    "cg-report"
   ],
   "exposed": true
  }
 },
 {
  "name": "storage-access",
  "owner": {
   "login": "privacycg"
  },
  "homepageUrl": "https://privacycg.github.io/storage-access/",
  "description": "The Storage Access API",
  "isArchived": false,
  "isPrivate": false,
  "w3cjson": {
   "group": [
    "cg/privacycg"
   ],
   "contacts": [
    "hober",
    "TanviHacks",
    "erik-anderson",
    "wseltzer",
    "weiler"
   ],
   "repo-type": [
    "cg-report"
   ],
   "exposed": true
  }
 },
 {
  "name": "storage-access-headers",
  "owner": {
   "login": "privacycg"
  },
  "homepageUrl": "https://privacycg.github.io/storage-access-headers/",
  "description": "Proposal for HTTP headers related to the Storage Access API",
  "isArchived": false,
  "isPrivate": false,
  "w3cjson": {
   "group": [
    "cg/privacycg"
   ],
   "contacts": [
    "hober",
    "martinthomson",
    "erik-anderson"
   ],
   "repo-type": [
    "cg-report"
   ],
   "exposed": true
  }
 },
 {
  "name": "storage-partitioning",
  "owner": {
   "login": "privacycg"
  },
  "homepageUrl": "https://privacycg.github.io/storage-partitioning/",
  "description": "Client-Side Storage Partitioning",
  "isArchived": false,
  "isPrivate": false,
  "w3cjson": {
   "group": [
    "cg/privacycg"
   ],
   "contacts": [
    "hober",
    "TanviHacks",
    "erik-anderson",
    "wseltzer",
    "weiler"
   ],
   "repo-type": [
    "cg-report"
   ],
   "exposed": true
  }
 },
 {
  "name": "template",
  "owner": {
   "login": "privacycg"
  },
  "description": "Template repository for a CG proposal or work item.",
  "isArchived": false,
  "isPrivate": false,
  "w3cjson": {
   "group": [
    "cg/privacycg"
   ],
   "contacts": [
    "hober",
    "martinthomson",
    "erik-anderson"
   ],
   "repo-type": [
    "cg-report"
   ],
   "exposed": true
  }
 }
]