{
 "id": 106721,
 "name": "Audio Description Community Group",
 "is_closed": false,
 "creation-date": "2018-04-19",
 "description": "Mission: To create an open standard file format to support audio description all the way from scripting to mixing.\r\n\r\nScope: To agree requirements and propose a workable open standard file format for audio description, probably a profile of TTML2, with the intention of moving to the Rec track within a Working Group.\r\n\r\nDeliverables:\r\n\r\n<ul>\r\n<li>Requirements document</li>\r\n<li>Draft specification document</li>\r\n<li>Explainer</li>\r\n</ul>",
 "shortname": "audio-description",
 "spec-publisher": true,
 "discr": "w3cgroup",
 "_links": {
  "self": {
   "href": "https://api.w3.org/groups/cg/audio-description"
  },
  "homepage": {
   "href": "https://www.w3.org/community/audio-description/"
  },
  "users": {
   "href": "https://api.w3.org/groups/cg/audio-description/users"
  },
  "services": {
   "href": "https://api.w3.org/groups/cg/audio-description/services"
  },
  "chairs": {
   "href": "https://api.w3.org/groups/cg/audio-description/chairs"
  },
  "join": {
   "href": "https://www.w3.org/community/audio-description/join"
  },
  "participations": {
   "href": "https://api.w3.org/groups/cg/audio-description/participations"
  }
 },
 "type": "community group",
 "tr-publisher": false,
 "group-type": "cg",
 "identifier": "cg/audio-description",
 "services": [
  {
   "href": "https://api.w3.org/services/15477",
   "title": "GitHub repository (Version Control)",
   "details": {
    "closed": false,
    "type": "repository",
    "link": "https://github.com/w3c/adpt",
    "shortdesc": "GitHub repository",
    "_links": {
     "self": {
      "href": "https://api.w3.org/services/15477"
     },
     "groups": {
      "href": "https://api.w3.org/services/15477/groups"
     }
    }
   }
  },
  {
   "href": "https://api.w3.org/services/13785",
   "title": "internal-audio-description (Mailing List)",
   "details": {
    "closed": false,
    "type": "lists",
    "link": "https://lists.w3.org/Archives/Member/internal-audio-description/",
    "shortdesc": "internal-audio-description",
    "_links": {
     "self": {
      "href": "https://api.w3.org/services/13785"
     },
     "groups": {
      "href": "https://api.w3.org/services/13785/groups"
     }
    }
   }
  },
  {
   "href": "https://api.w3.org/services/13782",
   "title": "IRC (Chat)",
   "details": {
    "closed": false,
    "type": "chat",
    "link": "irc://irc.w3.org/#audio-description",
    "shortdesc": "IRC",
    "_links": {
     "self": {
      "href": "https://api.w3.org/services/13782"
     },
     "groups": {
      "href": "https://api.w3.org/services/13782/groups"
     }
    }
   }
  },
  {
   "href": "https://api.w3.org/services/13783",
   "title": "public-audio-description (Mailing List)",
   "details": {
    "closed": false,
    "type": "lists",
    "link": "https://lists.w3.org/Archives/Public/public-audio-description/",
    "shortdesc": "public-audio-description",
    "_links": {
     "self": {
      "href": "https://api.w3.org/services/13783"
     },
     "groups": {
      "href": "https://api.w3.org/services/13783/groups"
     }
    }
   }
  },
  {
   "href": "https://api.w3.org/services/13781",
   "title": "RSS (RSS)",
   "details": {
    "closed": false,
    "type": "rss",
    "link": "https://www.w3.org/community/audio-description/feed/",
    "shortdesc": "RSS",
    "_links": {
     "self": {
      "href": "https://api.w3.org/services/13781"
     },
     "groups": {
      "href": "https://api.w3.org/services/13781/groups"
     }
    }
   }
  }
 ]
}