{"id":49161,"name":"Community I/O Community Group","is_closed":false,"description":"This group will focus on applying current information technologies to create a foundation of infrastructure for organizing the flow of resources and support with services within human community.\r\nAll peers (individuals or projects) can state their needs (input) and offers (output).\r\nUsing Semantic Web, Federated Social Web and other related technologies people can develop various approaches of connecting those needs and offers. Including variants with and without use of currencies.","shortname":"community-io","discr":"w3cgroup","type":"community group","_links":{"self":{"href":"https://api.w3.org/groups/cg/community-io"},"homepage":{"href":"https://www.w3.org/community/community-io/"},"users":{"href":"https://api.w3.org/groups/cg/community-io/users"},"services":{"href":"https://api.w3.org/groups/cg/community-io/services"},"chairs":{"href":"https://api.w3.org/groups/cg/community-io/chairs"},"join":{"href":"https://www.w3.org/community/community-io/join"},"participations":{"href":"https://api.w3.org/groups/cg/community-io/participations"}},"identifier":"cg/community-io"}