{
 "id": 157595,
 "name": "Threat Modeling Community Group",
 "is_closed": false,
 "creation-date": "2024-07-03",
 "description": "The group's purpose is to provide a meeting point for Security, Privacy, and Human Rights experts, along with technology domain experts, to create Threat Models together.\r\n\r\nThis group will not publish Specifications.",
 "shortname": "tmcg",
 "spec-publisher": false,
 "discr": "w3cgroup",
 "_links": {
  "self": {
   "href": "https://api.w3.org/groups/cg/tmcg"
  },
  "homepage": {
   "href": "https://www.w3.org/community/tmcg/"
  },
  "users": {
   "href": "https://api.w3.org/groups/cg/tmcg/users"
  },
  "services": {
   "href": "https://api.w3.org/groups/cg/tmcg/services"
  },
  "chairs": {
   "href": "https://api.w3.org/groups/cg/tmcg/chairs"
  },
  "join": {
   "href": "https://www.w3.org/community/tmcg/join"
  },
  "participations": {
   "href": "https://api.w3.org/groups/cg/tmcg/participations"
  }
 },
 "type": "community group",
 "tr-publisher": false,
 "group-type": "cg",
 "identifier": "cg/tmcg",
 "services": [
  {
   "href": "https://api.w3.org/services/43919",
   "title": "GitHub (Version Control)",
   "details": {
    "closed": false,
    "type": "repository",
    "link": "https://github.com/w3c-cg/threat-modeling",
    "shortdesc": "GitHub",
    "_links": {
     "self": {
      "href": "https://api.w3.org/services/43919"
     },
     "groups": {
      "href": "https://api.w3.org/services/43919/groups"
     }
    }
   }
  },
  {
   "href": "https://api.w3.org/services/43917",
   "title": "internal-tmcg (Mailing List)",
   "details": {
    "closed": false,
    "type": "lists",
    "link": "https://lists.w3.org/Archives/Member/internal-tmcg/",
    "shortdesc": "internal-tmcg",
    "_links": {
     "self": {
      "href": "https://api.w3.org/services/43917"
     },
     "groups": {
      "href": "https://api.w3.org/services/43917/groups"
     }
    }
   }
  },
  {
   "href": "https://api.w3.org/services/43915",
   "title": "IRC (Chat)",
   "details": {
    "closed": false,
    "type": "chat",
    "link": "irc://irc.w3.org/#tmcg",
    "shortdesc": "IRC",
    "_links": {
     "self": {
      "href": "https://api.w3.org/services/43915"
     },
     "groups": {
      "href": "https://api.w3.org/services/43915/groups"
     }
    }
   }
  },
  {
   "href": "https://api.w3.org/services/43916",
   "title": "public-tmcg (Mailing List)",
   "details": {
    "closed": false,
    "type": "lists",
    "link": "https://lists.w3.org/Archives/Public/public-tmcg/",
    "shortdesc": "public-tmcg",
    "_links": {
     "self": {
      "href": "https://api.w3.org/services/43916"
     },
     "groups": {
      "href": "https://api.w3.org/services/43916/groups"
     }
    }
   }
  },
  {
   "href": "https://api.w3.org/services/43914",
   "title": "RSS (RSS)",
   "details": {
    "closed": false,
    "type": "rss",
    "link": "https://www.w3.org/community/tmcg/feed/",
    "shortdesc": "RSS",
    "_links": {
     "self": {
      "href": "https://api.w3.org/services/43914"
     },
     "groups": {
      "href": "https://api.w3.org/services/43914/groups"
     }
    }
   }
  }
 ]
}