[
 {
  "name": "admin",
  "owner": {
   "login": "gpuweb"
  },
  "description": "Administrative documents",
  "isArchived": false,
  "isPrivate": false,
  "w3cjson": {
   "group": [
    "cg/gpu"
   ],
   "exposed": true
  }
 },
 {
  "name": "cts",
  "owner": {
   "login": "gpuweb"
  },
  "homepageUrl": "https://gpuweb.github.io/cts/",
  "description": "WebGPU Conformance Test Suite",
  "isArchived": false,
  "isPrivate": false,
  "w3cjson": {
   "group": [
    "cg/gpu",
    "wg/gpu"
   ],
   "contacts": [
    "tidoust",
    "Kangz",
    "grorg"
   ],
   "repo-type": [
    "tests"
   ],
   "exposed": true
  }
 },
 {
  "name": "gpuweb",
  "owner": {
   "login": "gpuweb"
  },
  "homepageUrl": "https://webgpu.org",
  "description": "Where the GPU for the Web work happens!",
  "isArchived": false,
  "isPrivate": false,
  "w3cjson": {
   "group": [
    "cg/gpu",
    "wg/gpu"
   ],
   "contacts": [
    "tidoust",
    "Kangz",
    "kdashg"
   ],
   "repo-type": [
    "cg-report",
    "rec-track"
   ],
   "exposed": true
  }
 },
 {
  "name": "gpuweb-cts-pr-previews",
  "owner": {
   "login": "gpuweb"
  },
  "isArchived": false,
  "isPrivate": false,
  "w3cjson": {
   "group": [
    "cg/gpu"
   ],
   "exposed": true
  }
 },
 {
  "name": "gpuweb-pr-previews",
  "owner": {
   "login": "gpuweb"
  },
  "description": "Pull request previews for gpuweb/gpuweb specifications.",
  "isArchived": false,
  "isPrivate": false,
  "w3cjson": {
   "group": [
    "cg/gpu"
   ],
   "exposed": true
  }
 },
 {
  "name": "gpuweb.github.io",
  "owner": {
   "login": "gpuweb"
  },
  "homepageUrl": "https://gpuweb.github.io/gpuweb/",
  "description": "Redirects to:",
  "isArchived": false,
  "isPrivate": false,
  "w3cjson": {
   "group": [
    "cg/gpu"
   ],
   "exposed": true
  }
 },
 {
  "name": "tree-sitter-wgsl",
  "owner": {
   "login": "gpuweb"
  },
  "isArchived": false,
  "isPrivate": false,
  "w3cjson": {
   "group": [
    "cg/gpu"
   ],
   "exposed": true
  }
 },
 {
  "name": "types",
  "owner": {
   "login": "gpuweb"
  },
  "homepageUrl": "https://www.npmjs.com/package/@webgpu/types",
  "description": "TypeScript type definitions for WebGPU https://gpuweb.github.io/types/ ",
  "isArchived": false,
  "isPrivate": false,
  "w3cjson": {
   "group": [
    "cg/gpu"
   ],
   "exposed": true
  }
 }
]